CMakeLists.txt
LICENSE
MANIFEST.in
README.md
requirements.txt
setup.py
cyber/binary.cc
cyber/binary.h
cyber/base/atomic_hash_map.h
cyber/base/atomic_rw_lock.h
cyber/base/bounded_queue.h
cyber/base/concurrent_object_pool.h
cyber/base/for_each.h
cyber/base/macros.h
cyber/base/object_pool.h
cyber/base/reentrant_rw_lock.h
cyber/base/rw_lock_guard.h
cyber/base/signal.h
cyber/base/thread_pool.h
cyber/base/thread_safe_queue.h
cyber/base/unbounded_queue.h
cyber/base/wait_strategy.h
cyber/common/environment.h
cyber/common/file.cc
cyber/common/file.h
cyber/common/global_data.cc
cyber/common/global_data.h
cyber/common/log.h
cyber/common/macros.h
cyber/common/time_conversion.h
cyber/common/types.h
cyber/common/util.h
cyber/jni/internal/jni_record.cc
cyber/message/message_header.h
cyber/message/message_traits.h
cyber/message/protobuf_factory.cc
cyber/message/protobuf_factory.h
cyber/message/protobuf_traits.h
cyber/message/py_message.h
cyber/message/py_message_traits.h
cyber/message/raw_message.h
cyber/message/raw_message_traits.h
cyber/proto/choreography_conf.proto
cyber/proto/classic_conf.proto
cyber/proto/component_conf.proto
cyber/proto/cyber_conf.proto
cyber/proto/dag_conf.proto
cyber/proto/perf_conf.proto
cyber/proto/proto_desc.proto
cyber/proto/qos_profile.proto
cyber/proto/record.proto
cyber/proto/run_mode_conf.proto
cyber/proto/scheduler_conf.proto
cyber/proto/transport_conf.proto
cyber/python/internal/py_record.cc
cyber/python/internal/py_record.h
cyber/record/header_builder.cc
cyber/record/header_builder.h
cyber/record/record_base.h
cyber/record/record_message.h
cyber/record/record_reader.cc
cyber/record/record_reader.h
cyber/record/record_viewer.cc
cyber/record/record_viewer.h
cyber/record/record_writer.cc
cyber/record/record_writer.h
cyber/record/file/record_file_base.cc
cyber/record/file/record_file_base.h
cyber/record/file/record_file_reader.cc
cyber/record/file/record_file_reader.h
cyber/record/file/record_file_writer.cc
cyber/record/file/record_file_writer.h
cyber_record_util.egg-info/PKG-INFO
cyber_record_util.egg-info/SOURCES.txt
cyber_record_util.egg-info/dependency_links.txt
cyber_record_util.egg-info/not-zip-safe
cyber_record_util.egg-info/top_level.txt