Metadata-Version: 2.1
Name: cyber-record-util
Version: 12
Summary: standalone apollo cyber record reader/writer
Home-page: https://github.com/weimzh/cyber-record/
Author: Wei Mingzhi
Author-email: whistler@member.fsf.org
License-File: LICENSE
